{
    "Title": "The Nîn-in-Eilph",
    "Slug": "The-Nîn-in-Eilph",
    "Product": "The Nîn-in-Eilph",
    "Number": 4,
    "QuestCards": [
        {
            "Title": "Fleeing from Tharbad",
            "Slug": "Fleeing-from-Tharbad-NiE",
            "IsUnique": false,
            "CardType": "Quest",
            "CardSubType": "None",
            "Sphere": null,
            "Front": {
                "Subtitle": null,
                "ImagePath": "https://s3.amazonaws.com/hallofbeorn-resources/Images/Cards/The-Nin-in-Eilph/Fleeing-from-Tharbad-1A.jpg",
                "Stats": {
                    "StageNumber": "1A"
                },
                "Traits": [],
                "Keywords": [],
                "Text": [
                    "Setup: The first player takes control of Nalir. Set the Ancient Marsh-dweller aside, out of play. Each player searches the encounter deck for a different location and adds it to the staging area. Shuffle the encounter deck."
                ],
                "Shadow": null,
                "FlavorText": "You`ve entered the vast marshlands of the Nin-in-Eilph with Nalir in order to escape Bellach and his Orcs. Now, you must cross the swamp in order to reach Hollin on the other side."
            },
            "Back": {
                "Subtitle": null,
                "ImagePath": "https://s3.amazonaws.com/hallofbeorn-resources/Images/Cards/The-Nin-in-Eilph/Fleeing-from-Tharbad-1B.jpg",
                "Stats": {
                    "StageNumber": "1B",
                    "QuestPoints": "0"
                },
                "Traits": [],
                "Keywords": [],
                "Text": [
                    "When Revealed: Advance to a random stage 2A."
                ],
                "Shadow": null,
                "FlavorText": "No traveller has entered the Nîn-in-Eilph for an age and there is no path through the shifting marshland. You must find your own way across the treacherous bog."
            },
            "CardSet": "The Nîn-in-Eilph",
            "EncounterInfo": {
                "EncounterSet": "The Nîn-in-Eilph",
                "EasyModeQuantity": 0,
                "IncludedEncounterSets": [
                    "Weary Travelers"
                ],
                "StageNumber": 1,
                "StageLetter": "A"
            },
            "Number": 94,
            "Quantity": 1,
            "Artist": "Igor Kieryluk",
            "HasErrata": false,
            "OctgnGuid": null,
            "RingsDbCardId": null,
            "RingsDbPopularity": 0,
            "RingsDbVotes": 0,
            "Categories": null
        },
        {
            "Title": "Through the Marsh",
            "Slug": "Through-the-Marsh-No-End-in-Sight-NiE",
            "IsUnique": false,
            "CardType": "Quest",
            "CardSubType": "None",
            "Sphere": null,
            "Front": {
                "Subtitle": null,
                "ImagePath": "https://s3.amazonaws.com/hallofbeorn-resources/Images/Cards/The-Nin-in-Eilph/Through-the-Marsh-No-End-in-Sight-2A.jpg",
                "Stats": {
                    "StageNumber": "2A"
                },
                "Traits": [],
                "Keywords": [],
                "Text": [
                    "When Revealed: Raise each player`s threat by 1."
                ],
                "Shadow": null,
                "FlavorText": "As you trudge through endless swamp, you begin to wonder if you will ever reach the other side."
            },
            "Back": {
                "Subtitle": null,
                "ImagePath": "https://s3.amazonaws.com/hallofbeorn-resources/Images/Cards/The-Nin-in-Eilph/Through-the-Marsh-No-End-in-Sight-2B.jpg",
                "Stats": {
                    "StageNumber": "2B",
                    "QuestPoints": "13"
                },
                "Traits": [],
                "Keywords": [],
                "Text": [
                    "Time 3.",
                    "Forced: After the last time counter is removed from this stage, advance to a different stage 2A at random. Return this stage to the quest deck.",
                    "Player card effects cannot be used to gain resources or draw cards.",
                    "Forced: When the players defeat this stage, advance to a random stage 3A."
                ],
                "Shadow": null,
                "FlavorText": null
            },
            "CardSet": "The Nîn-in-Eilph",
            "EncounterInfo": {
                "EncounterSet": "The Nîn-in-Eilph",
                "EasyModeQuantity": 0,
                "IncludedEncounterSets": [
                    "Weary Travelers"
                ],
                "StageNumber": 2,
                "StageLetter": "A"
            },
            "Number": 95,
            "Quantity": 1,
            "Artist": "Mariusz Gandzel",
            "HasErrata": false,
            "OctgnGuid": null,
            "RingsDbCardId": null,
            "RingsDbPopularity": 0,
            "RingsDbVotes": 0,
            "Categories": null
        },
        {
            "Title": "Through the Marsh",
            "Slug": "Through-the-Marsh-A-Weary-Passage-NiE",
            "IsUnique": false,
            "CardType": "Quest",
            "CardSubType": "None",
            "Sphere": null,
            "Front": {
                "Subtitle": null,
                "ImagePath": "https://s3.amazonaws.com/hallofbeorn-resources/Images/Cards/The-Nin-in-Eilph/Through-the-Marsh-A-Weary-Passage-2A.jpg",
                "Stats": {
                    "StageNumber": "2A"
                },
                "Traits": [],
                "Keywords": [],
                "Text": [
                    "When Revealed: Raise each player`s threat by 1."
                ],
                "Shadow": null,
                "FlavorText": "As you trudge through endless swamp, you begin to wonder if you will ever reach the other side."
            },
            "Back": {
                "Subtitle": null,
                "ImagePath": "https://s3.amazonaws.com/hallofbeorn-resources/Images/Cards/The-Nin-in-Eilph/Through-the-Marsh-A-Weary-Passage-2B.jpg",
                "Stats": {
                    "StageNumber": "2B",
                    "QuestPoints": "13"
                },
                "Traits": [],
                "Keywords": [],
                "Text": [
                    "Time 3.",
                    "Forced: After the last time counter is removed from this stage, advance to a different stage 2A at random. Return this stage to the quest deck.",
                    "In order to commit characters to the quest, a player must first discard a card at random from his hand.",
                    "Forced: When the players defeat this stage, advance to a random stage 3A."
                ],
                "Shadow": null,
                "FlavorText": null
            },
            "CardSet": "The Nîn-in-Eilph",
            "EncounterInfo": {
                "EncounterSet": "The Nîn-in-Eilph",
                "EasyModeQuantity": 0,
                "IncludedEncounterSets": [
                    "Weary Travelers"
                ],
                "StageNumber": 2,
                "StageLetter": "A"
            },
            "Number": 96,
            "Quantity": 1,
            "Artist": "Mariusz Gandzel",
            "HasErrata": false,
            "OctgnGuid": null,
            "RingsDbCardId": null,
            "RingsDbPopularity": 0,
            "RingsDbVotes": 0,
            "Categories": null
        },
        {
            "Title": "Through the Marsh",
            "Slug": "Through-the-Marsh-A-Forgotten-Land-NiE",
            "IsUnique": false,
            "CardType": "Quest",
            "CardSubType": "None",
            "Sphere": null,
            "Front": {
                "Subtitle": null,
                "ImagePath": "https://s3.amazonaws.com/hallofbeorn-resources/Images/Cards/The-Nin-in-Eilph/Through-the-Marsh-A-Forgotten-Land-2A.jpg",
                "Stats": {
                    "StageNumber": "2A"
                },
                "Traits": [],
                "Keywords": [],
                "Text": [
                    "When Revealed: Raise each player`s threat by 1."
                ],
                "Shadow": null,
                "FlavorText": "As you trudge through endless swamp, you begin to wonder if you will ever reach the other side."
            },
            "Back": {
                "Subtitle": null,
                "ImagePath": "https://s3.amazonaws.com/hallofbeorn-resources/Images/Cards/The-Nin-in-Eilph/Through-the-Marsh-A-Forgotten-Land-2B.jpg",
                "Stats": {
                    "StageNumber": "2B",
                    "QuestPoints": "13"
                },
                "Traits": [],
                "Keywords": [],
                "Text": [
                    "Time 3.",
                    "Forced: After the last time counter is removed from this stage, advance to a different stage 2A at random. Return this stage to the quest deck.",
                    "Each player cannot play more than 1 card each round.",
                    "Forced: When the players defeat this stage, advance to a random stage 3A."
                ],
                "Shadow": null,
                "FlavorText": null
            },
            "CardSet": "The Nîn-in-Eilph",
            "EncounterInfo": {
                "EncounterSet": "The Nîn-in-Eilph",
                "EasyModeQuantity": 0,
                "IncludedEncounterSets": [
                    "Weary Travelers"
                ],
                "StageNumber": 2,
                "StageLetter": "A"
            },
            "Number": 97,
            "Quantity": 1,
            "Artist": "Mariusz Gandzel",
            "HasErrata": false,
            "OctgnGuid": null,
            "RingsDbCardId": null,
            "RingsDbPopularity": 0,
            "RingsDbVotes": 0,
            "Categories": null
        },
        {
            "Title": "Lost in the Swanfleet",
            "Slug": "Lost-in-the-Swanfleet-Impassable-Marshland-NiE",
            "IsUnique": false,
            "CardType": "Quest",
            "CardSubType": "None",
            "Sphere": null,
            "Front": {
                "Subtitle": null,
                "ImagePath": "https://s3.amazonaws.com/hallofbeorn-resources/Images/Cards/The-Nin-in-Eilph/Lost-in-the-Swanfleet-Impassable-Marshland-3A.jpg",
                "Stats": {
                    "StageNumber": "3A"
                },
                "Traits": [],
                "Keywords": [],
                "Text": [
                    "When Revealed: Raise each player`s threat by 1. Add Ancient Marsh-dweller to the staging area (from out of play or engaged with a player) and heal all damage from it."
                ],
                "Shadow": null,
                "FlavorText": "Lost as you are, your presence in the marsh has not gone unnoticed. An ancient and foul swamp creature stalks your company..."
            },
            "Back": {
                "Subtitle": null,
                "ImagePath": "https://s3.amazonaws.com/hallofbeorn-resources/Images/Cards/The-Nin-in-Eilph/Lost-in-the-Swanfleet-Impassable-Marshland-3B.jpg",
                "Stats": {
                    "StageNumber": "3B",
                    "QuestPoints": "16"
                },
                "Traits": [],
                "Keywords": [],
                "Text": [
                    "Time 3.",
                    "Forced: After the last time counter is removed from this stage, advance to a different stage 3A at random. Return this stage to the quest deck.",
                    "Each location in play gets +1 Threat."
                ],
                "Shadow": null,
                "FlavorText": "Despite the size of the creatures hunting you, the swamp itself is your worst enemy. The ground sinks down beneath you and the mud pulls the boots off your feet. Every step forward is a struggle..."
            },
            "CardSet": "The Nîn-in-Eilph",
            "EncounterInfo": {
                "EncounterSet": "The Nîn-in-Eilph",
                "EasyModeQuantity": 0,
                "IncludedEncounterSets": [
                    "Weary Travelers"
                ],
                "StageNumber": 3,
                "StageLetter": "A"
            },
            "Number": 98,
            "Quantity": 1,
            "Artist": "Silver Saaremäel",
            "HasErrata": false,
            "OctgnGuid": null,
            "RingsDbCardId": null,
            "RingsDbPopularity": 0,
            "RingsDbVotes": 0,
            "Categories": null
        },
        {
            "Title": "Lost in the Swanfleet",
            "Slug": "Lost-in-the-Swanfleet-A-Treacherous-Swamp-NiE",
            "IsUnique": false,
            "CardType": "Quest",
            "CardSubType": "None",
            "Sphere": null,
            "Front": {
                "Subtitle": null,
                "ImagePath": "https://s3.amazonaws.com/hallofbeorn-resources/Images/Cards/The-Nin-in-Eilph/Lost-in-the-Swanfleet-A-Treacherous-Swamp-3A.jpg",
                "Stats": {
                    "StageNumber": "3A"
                },
                "Traits": [],
                "Keywords": [],
                "Text": [
                    "When Revealed: Raise each player`s threat by 1. Add Ancient Marsh-dweller to the staging area (from out of play or engaged with a player) and heal all damage from it."
                ],
                "Shadow": null,
                "FlavorText": "Lost as you are, your presence in the marsh has not gone unnoticed. An ancient and foul swamp creature stalks your company..."
            },
            "Back": {
                "Subtitle": null,
                "ImagePath": "https://s3.amazonaws.com/hallofbeorn-resources/Images/Cards/The-Nin-in-Eilph/Lost-in-the-Swanfleet-A-Treacherous-Swamp-3B.jpg",
                "Stats": {
                    "StageNumber": "3B",
                    "QuestPoints": "16"
                },
                "Traits": [],
                "Keywords": [],
                "Text": [
                    "Time 3.",
                    "Forced: After the last time counter is removed from this stage, advance to a different stage 3A at random. Return this stage to the quest deck.",
                    "Each player cannot ready more than 5 characters during the refresh phase."
                ],
                "Shadow": null,
                "FlavorText": "After wandering aimlessly for so long, harried by foul creatues, your resolve begins to waver and your companions collapse from exhaustion. If you cannot find a way across, the swamp will erase all evidence of your passage..."
            },
            "CardSet": "The Nîn-in-Eilph",
            "EncounterInfo": {
                "EncounterSet": "The Nîn-in-Eilph",
                "EasyModeQuantity": 0,
                "IncludedEncounterSets": [
                    "Weary Travelers"
                ],
                "StageNumber": 3,
                "StageLetter": "A"
            },
            "Number": 99,
            "Quantity": 1,
            "Artist": "Silver Saaremäel",
            "HasErrata": false,
            "OctgnGuid": null,
            "RingsDbCardId": null,
            "RingsDbPopularity": 0,
            "RingsDbVotes": 0,
            "Categories": null
        },
        {
            "Title": "Lost in the Swanfleet",
            "Slug": "Lost-in-the-Swanfleet-Creatures-of-a-Forgotten-Age-NiE",
            "IsUnique": false,
            "CardType": "Quest",
            "CardSubType": "None",
            "Sphere": null,
            "Front": {
                "Subtitle": null,
                "ImagePath": "https://s3.amazonaws.com/hallofbeorn-resources/Images/Cards/The-Nin-in-Eilph/Lost-in-the-Swanfleet-Creatures-of-a-Forgotten-Age-3A.jpg",
                "Stats": {
                    "StageNumber": "3A"
                },
                "Traits": [],
                "Keywords": [],
                "Text": [
                    "When Revealed: Raise each player`s threat by 1. Add Ancient Marsh-dweller to the staging area (from out of play or engaged with a player) and heal all damage from it."
                ],
                "Shadow": null,
                "FlavorText": "Lost as you are, your presence in the marsh has not gone unnoticed. An ancient and foul swamp creature stalks your company..."
            },
            "Back": {
                "Subtitle": null,
                "ImagePath": "https://s3.amazonaws.com/hallofbeorn-resources/Images/Cards/The-Nin-in-Eilph/Lost-in-the-Swanfleet-Creatures-of-a-Forgotten-Age-3B.jpg",
                "Stats": {
                    "StageNumber": "3B",
                    "QuestPoints": "16"
                },
                "Traits": [],
                "Keywords": [],
                "Text": [
                    "Time 3.",
                    "Forced: After the last time counter is removed from this stage, advance to a different stage 3A at random. Return this stage to the quest deck.",
                    "Each enemy in the staging area gets -20 engagement cost."
                ],
                "Shadow": null,
                "FlavorText": "As if the swamp itself was not bad enough, its foul denizens swarm around you, their serpentine forms slithering through the murky water that rises to your waist..."
            },
            "CardSet": "The Nîn-in-Eilph",
            "EncounterInfo": {
                "EncounterSet": "The Nîn-in-Eilph",
                "EasyModeQuantity": 0,
                "IncludedEncounterSets": [
                    "Weary Travelers"
                ],
                "StageNumber": 3,
                "StageLetter": "A"
            },
            "Number": 100,
            "Quantity": 1,
            "Artist": "Silver Saaremäel",
            "HasErrata": false,
            "OctgnGuid": null,
            "RingsDbCardId": null,
            "RingsDbPopularity": 0,
            "RingsDbVotes": 0,
            "Categories": null
        },
        {
            "Title": "Out of the Swamp",
            "Slug": "Out-of-the-Swamp-NiE",
            "IsUnique": false,
            "CardType": "Quest",
            "CardSubType": "None",
            "Sphere": null,
            "Front": {
                "Subtitle": null,
                "ImagePath": "https://s3.amazonaws.com/hallofbeorn-resources/Images/Cards/The-Nin-in-Eilph/Out-of-the-Swamp-4A.jpg",
                "Stats": {
                    "StageNumber": "4A"
                },
                "Traits": [],
                "Keywords": [],
                "Text": [
                    "When Revealed: Add Ancient Marsh-dweller to the staging area (from out of play or engaged with a player) and heal all damage on it. Then Ancient Marsh-dweller makes an attack against each player in player order."
                ],
                "Shadow": null,
                "FlavorText": "Beyond all hope, you have reached the edge of the swamp! You can see the gentle rise of the hills in the distance, but the huge marsh-dweller that has pursued your company now lies between you and dry land."
            },
            "Back": {
                "Subtitle": null,
                "ImagePath": "https://s3.amazonaws.com/hallofbeorn-resources/Images/Cards/The-Nin-in-Eilph/Out-of-the-Swamp-4B.jpg",
                "Stats": {
                    "StageNumber": "4B",
                    "QuestPoints": "-"
                },
                "Traits": [],
                "Keywords": [],
                "Text": [
                    "Time 2.",
                    "Forced: After the last time counter is removed from this stage, Ancient Marsh-dweller makes an attack against each player in order. Place 2 time counters on this stage.",
                    "When Ancient Marsh-dweller is defeated, the players win the game."
                ],
                "Shadow": null,
                "FlavorText": null
            },
            "CardSet": "The Nîn-in-Eilph",
            "EncounterInfo": {
                "EncounterSet": "The Nîn-in-Eilph",
                "EasyModeQuantity": 0,
                "IncludedEncounterSets": [
                    "Weary Travelers"
                ],
                "StageNumber": 4,
                "StageLetter": "A"
            },
            "Number": 101,
            "Quantity": 1,
            "Artist": "Rafał Hrynkiewicz",
            "HasErrata": false,
            "OctgnGuid": null,
            "RingsDbCardId": null,
            "RingsDbPopularity": 0,
            "RingsDbVotes": 0,
            "Categories": null
        }
    ],
    "ScenarioCards": [
        {
            "EncounterSet": "The Nîn-in-Eilph",
            "Title": "Ancient Marsh-dweller",
            "Slug": "Ancient-Marsh-dweller-NiE",
            "NormalQuantity": 1,
            "EasyQuantity": 1,
            "NightmareQuantity": 1
        },
        {
            "EncounterSet": "The Nîn-in-Eilph",
            "Title": "Fen of Reeds",
            "Slug": "Fen-of-Reeds-NiE",
            "NormalQuantity": 3,
            "EasyQuantity": 2,
            "NightmareQuantity": 3
        },
        {
            "EncounterSet": "The Nîn-in-Eilph",
            "Title": "Finger of Glanduin",
            "Slug": "Finger-of-Glanduin-NiE",
            "NormalQuantity": 3,
            "EasyQuantity": 3,
            "NightmareQuantity": 3
        },
        {
            "EncounterSet": "The Nîn-in-Eilph",
            "Title": "Giant Swamp Adder",
            "Slug": "Giant-Swamp-Adder-NiE",
            "NormalQuantity": 4,
            "EasyQuantity": 3,
            "NightmareQuantity": 4
        },
        {
            "EncounterSet": "The Nîn-in-Eilph",
            "Title": "Hidden Eyot",
            "Slug": "Hidden-Eyot-NiE",
            "NormalQuantity": 2,
            "EasyQuantity": 2,
            "NightmareQuantity": 2
        },
        {
            "EncounterSet": "The Nîn-in-Eilph",
            "Title": "Nalir",
            "Slug": "Nalir-NiE",
            "NormalQuantity": 1,
            "EasyQuantity": 1,
            "NightmareQuantity": 1
        },
        {
            "EncounterSet": "The Nîn-in-Eilph",
            "Title": "Neekerbreekers",
            "Slug": "Neekerbreekers-NiE",
            "NormalQuantity": 3,
            "EasyQuantity": 3,
            "NightmareQuantity": 3
        },
        {
            "EncounterSet": "The Nîn-in-Eilph",
            "Title": "Remnants of Elder Days",
            "Slug": "Remnants-of-Elder-Days-NiE",
            "NormalQuantity": 1,
            "EasyQuantity": 0,
            "NightmareQuantity": 1
        },
        {
            "EncounterSet": "The Nîn-in-Eilph",
            "Title": "Shifting Marshland",
            "Slug": "Shifting-Marshland-NiE",
            "NormalQuantity": 3,
            "EasyQuantity": 2,
            "NightmareQuantity": 3
        },
        {
            "EncounterSet": "The Nîn-in-Eilph",
            "Title": "Sinking Bog",
            "Slug": "Sinking-Bog-NiE",
            "NormalQuantity": 3,
            "EasyQuantity": 3,
            "NightmareQuantity": 3
        },
        {
            "EncounterSet": "The Nîn-in-Eilph Nightmare",
            "Title": "Deadly Marsh Adder",
            "Slug": "Deadly-Marsh-Adder-NiEN",
            "NormalQuantity": 0,
            "EasyQuantity": 0,
            "NightmareQuantity": 3
        },
        {
            "EncounterSet": "The Nîn-in-Eilph Nightmare",
            "Title": "Desolate Meadow",
            "Slug": "Desolate-Meadow-NiEN",
            "NormalQuantity": 0,
            "EasyQuantity": 0,
            "NightmareQuantity": 3
        },
        {
            "EncounterSet": "The Nîn-in-Eilph Nightmare",
            "Title": "Peat Bog",
            "Slug": "Peat-Bog-NiEN",
            "NormalQuantity": 0,
            "EasyQuantity": 0,
            "NightmareQuantity": 4
        },
        {
            "EncounterSet": "The Nîn-in-Eilph Nightmare",
            "Title": "Quicksand",
            "Slug": "Quicksand-NiEN",
            "NormalQuantity": 0,
            "EasyQuantity": 0,
            "NightmareQuantity": 2
        },
        {
            "EncounterSet": "The Nîn-in-Eilph Nightmare",
            "Title": "Rotten Stench",
            "Slug": "Rotten-Stench-NiEN",
            "NormalQuantity": 0,
            "EasyQuantity": 0,
            "NightmareQuantity": 2
        },
        {
            "EncounterSet": "The Nîn-in-Eilph Nightmare",
            "Title": "Swarms of Mosquitoes",
            "Slug": "Swarms-of-Mosquitoes-NiEN",
            "NormalQuantity": 0,
            "EasyQuantity": 0,
            "NightmareQuantity": 3
        },
        {
            "EncounterSet": "The Nîn-in-Eilph Nightmare",
            "Title": "The Nîn-in-Eilph Nightmare",
            "Slug": "The-Nin-in-Eilph-Nightmare-NiEN",
            "NormalQuantity": 0,
            "EasyQuantity": 0,
            "NightmareQuantity": 1
        },
        {
            "EncounterSet": "Weary Travelers",
            "Title": "In Need of Rest",
            "Slug": "In-Need-of-Rest-VoI",
            "NormalQuantity": 2,
            "EasyQuantity": 1,
            "NightmareQuantity": 2
        },
        {
            "EncounterSet": "Weary Travelers",
            "Title": "Low on Provisions",
            "Slug": "Low-on-Provisions-VoI",
            "NormalQuantity": 3,
            "EasyQuantity": 2,
            "NightmareQuantity": 3
        },
        {
            "EncounterSet": "Weary Travelers",
            "Title": "Off Track",
            "Slug": "Off-Track-VoI",
            "NormalQuantity": 2,
            "EasyQuantity": 2,
            "NightmareQuantity": 2
        }
    ]
}